{
 "aggregate_function_based_on": "",
 "color": "#db9972",
 "creation": "2024-07-18 11:00:08.309396",
 "docstatus": 0,
 "doctype": "Number Card",
 "document_type": "Task Detail",
 "dynamic_filters_json": "[]",
 "filters_json": "[[\"Task Detail\",\"assigned_to\",\"is\",\"set\",false]]",
 "function": "Count",
 "idx": 0,
 "is_public": 0,
 "is_standard": 1,
 "label": "Assigned Task",
 "modified": "2024-07-18 11:13:14.766470",
 "modified_by": "Administrator",
 "module": "Plantmaintenance",
 "name": "Assigned Task",
 "owner": "Administrator",
 "parent_document_type": "",
 "report_function": "Sum",
 "show_percentage_stats": 0,
 "stats_time_interval": "Daily",
 "type": "Document Type"
}